LICENSE
MANIFEST.in
README
README.md
setup.py
django_is_core.egg-info/PKG-INFO
django_is_core.egg-info/SOURCES.txt
django_is_core.egg-info/dependency_links.txt
django_is_core.egg-info/not-zip-safe
django_is_core.egg-info/requires.txt
django_is_core.egg-info/top_level.txt
example/__init__.py
example/manage.py
example/dj/__init__.py
example/dj/urls.py
example/dj/wsgi.py
example/dj/apps/__init__.py
example/dj/apps/issue_tracker/__init__.py
example/dj/apps/issue_tracker/models.py
example/dj/apps/issue_tracker/cores/__init__.py
example/dj/apps/issue_tracker/cores/resources.py
example/dj/apps/issue_tracker/cores/views.py
example/dj/apps/issue_tracker/dynamo/__init__.py
example/dj/apps/issue_tracker/dynamo/core.py
example/dj/apps/issue_tracker/dynamo/models.py
example/dj/apps/issue_tracker/elasticsearch/__init__.py
example/dj/apps/issue_tracker/elasticsearch/core.py
example/dj/apps/issue_tracker/elasticsearch/models.py
example/dj/apps/issue_tracker/forms/__init__.py
example/dj/apps/issue_tracker/migrations/0001_initial.py
example/dj/apps/issue_tracker/migrations/0002_auto_20210401_1128.py
example/dj/apps/issue_tracker/migrations/__init__.py
example/dj/apps/issue_tracker/tests/__init__.py
example/dj/apps/issue_tracker/tests/dynamo.py
example/dj/apps/issue_tracker/tests/elasticsearch.py
example/dj/apps/issue_tracker/tests/factories.py
example/dj/apps/issue_tracker/tests/field_permissions.py
example/dj/apps/issue_tracker/tests/http_exceptions.py
example/dj/apps/issue_tracker/tests/permissions.py
example/dj/apps/issue_tracker/tests/rest.py
example/dj/apps/issue_tracker/tests/rest_permissions.py
example/dj/apps/issue_tracker/tests/test_case.py
example/dj/apps/issue_tracker/tests/ui_ordering.py
example/dj/apps/issue_tracker/tests/ui_permissions.py
example/dj/apps/issue_tracker/tests/utils.py
example/dj/settings/__init__.py
example/dj/settings/base.py
example/dj/settings/settings.py
is_core/__init__.py
is_core/actions.py
is_core/config.py
is_core/context_processors.py
is_core/loading.py
is_core/main.py
is_core/menu.py
is_core/middleware.py
is_core/patterns.py
is_core/response.py
is_core/site.py
is_core/version.py
is_core/auth/__init__.py
is_core/auth/permissions.py
is_core/auth/views.py
