Metadata-Version: 2.1
Name: django-is-core
Version: 2.23.7
Summary: Information systems core.
Home-page: https://github.com/matllubos/django-is-core
Author: Lubos Matl
Author-email: matllubos@gmail.com
License: BSD
Keywords: django,admin,information systems,REST
Platform: UNKNOWN
Classifier: Development Status :: 3 - Alpha
Classifier: Framework :: Django
Classifier: Intended Audience :: Developers
Classifier: License :: OSI Approved :: BSD License
Classifier: Operating System :: OS Independent
Classifier: Programming Language :: Python
Classifier: Topic :: Internet :: WWW/HTTP
